BezierCurve/__init__.py
BezierCurve/core.py
BezierCurve-0.0.2.dist-info/LICENSE
BezierCurve-0.0.2.dist-info/METADATA
BezierCurve-0.0.2.dist-info/WHEEL
BezierCurve-0.0.2.dist-info/top_level.txt
BezierCurve-0.0.2.dist-info/RECORD
