Metadata-Version: 2.1
Name: BezierCurve
Version: 0.0.2
Summary: BezierCurve for robotics
Author-email: Minchang Sung <tjdalsckd@gmail.com>
License: MIT License        
Project-URL: Homepage, https://github.com/tjdalsckd/BezierCurve
Project-URL: Bug Tracker, https://github.com/tjdalsckd/BezierCurve/issues
Classifier: Programming Language :: Python :: 3
Classifier: License :: OSI Approved :: MIT License
Classifier: Operating System :: OS Independent
Requires-Python: >=3.6
License-File: LICENSE
